docs/conf.py
docs/utils.py
psychopy_photoresearch/__init__.py
psychopy_photoresearch/pr.py
tests/__init__.py
tests/test_photometers.py
psychopy_photoresearch-0.0.3.dist-info/LICENSE
psychopy_photoresearch-0.0.3.dist-info/METADATA
psychopy_photoresearch-0.0.3.dist-info/WHEEL
psychopy_photoresearch-0.0.3.dist-info/top_level.txt
psychopy_photoresearch-0.0.3.dist-info/RECORD
